philip_pal/__init__.py
philip_pal/__main__.py
philip_pal/base_device.py
philip_pal/philip_if.py
philip_pal/philip_shell.py
philip_pal/serial_driver.py
philip_pal/mem_map/PHiLIP_map_t_1_0_0.csv
philip_pal/mem_map/PHiLIP_map_t_1_0_1.csv
philip_pal/mem_map/PHiLIP_map_t_1_0_2.csv
philip_pal/mem_map/PHiLIP_map_t_1_2_0.csv
philip_pal-1.2.0.dist-info/LICENSE
philip_pal-1.2.0.dist-info/METADATA
philip_pal-1.2.0.dist-info/WHEEL
philip_pal-1.2.0.dist-info/entry_points.txt
philip_pal-1.2.0.dist-info/top_level.txt
philip_pal-1.2.0.dist-info/RECORD
