Metadata-Version: 2.1
Name: philip-pal
Version: 1.2.0
Summary: Protocol abstraction and parser for PHiLIP
Home-page: https://github.com/riot-appstore/PHiLIP
Author: Kevin Weiss, Sebastian Meiling
Author-email: weiss.kevin604@gmail.com, s@mlng.net
License: MIT
Platform: any
Classifier: Programming Language :: Python :: 3
Classifier: License :: OSI Approved :: MIT License
Classifier: Operating System :: OS Independent
Classifier: Development Status :: 3 - Alpha
Classifier: Intended Audience :: Developers
Requires-Python: >=3.4.*
Requires-Dist: pyserial
Requires-Dist: tabulate
